<dvtablesearchentity dvtablesearchentityid="ba170b8b-96be-f011-bbd2-000d3a5a9505">
  <dvtablesearch>
    <dvtablesearchid>ea7c03d0-c10d-4022-b3bb-6d4197f0fd69</dvtablesearchid>
  </dvtablesearch>
  <entitylogicalname>17e3459b-6b5e-4c7a-bc6f-506c4b0314d8</entitylogicalname>
  <iscustomizable>1</iscustomizable>
  <name>K201902.pdf</name>
  <statecode>0</statecode>
  <statuscode>1</statuscode>
  <unstructuredfilesearchentityid>
    <unstructuredfilesearchentityid>a3f11f6e-3cbb-f011-bbd2-7ced8d709b8c</unstructuredfilesearchentityid>
  </unstructuredfilesearchentityid>
</dvtablesearchentity>