<dvtablesearchentity dvtablesearchentityid="d0860611-77be-f011-bbd2-000d3a5a9505">
  <dvtablesearch>
    <dvtablesearchid>5be7d29c-5488-4092-935a-dd147ca98298</dvtablesearchid>
  </dvtablesearch>
  <entitylogicalname>5635c9ab-7c0f-4f34-97c4-85c8a9395fa1</entitylogicalname>
  <iscustomizable>1</iscustomizable>
  <name>K062319.pdf</name>
  <statecode>0</statecode>
  <statuscode>1</statuscode>
  <unstructuredfilesearchentityid>
    <unstructuredfilesearchentityid>3ba37356-3dbd-f011-bbd2-000d3a36bee6</unstructuredfilesearchentityid>
  </unstructuredfilesearchentityid>
</dvtablesearchentity>