{
  "Test Name": "CD35 Immunostain",
  "Specimen Type": "Formalin-fixed, paraffin-embedded (FFPE) tissue sections",
  "Purpose": "To perform the analytical phase of CD35 immunostaining—preparation, staining, and initial quality assessment of tissue sections for subsequent pathological interpretation.",
  "Container": "Formalin-fixed, paraffin-embedded tissue block or positively charged microscope slide",
  "Equipment": "Microtome, water bath, staining racks, incubator, humidifying chamber, microscope"
}