<dvtablesearchentity dvtablesearchentityid="7d87f4c9-95be-f011-bbd2-000d3a5a9505">
  <dvtablesearch>
    <dvtablesearchid>4dbc395e-68c1-4fa8-b1e8-a98d24901173</dvtablesearchid>
  </dvtablesearch>
  <entitylogicalname>4ca78cb9-aa4e-4015-981b-1215d4194dde</entitylogicalname>
  <iscustomizable>1</iscustomizable>
  <name>K150819.pdf</name>
  <statecode>0</statecode>
  <statuscode>1</statuscode>
  <unstructuredfilesearchentityid>
    <unstructuredfilesearchentityid>95295def-3abd-f011-bbd2-000d3a36bee6</unstructuredfilesearchentityid>
  </unstructuredfilesearchentityid>
</dvtablesearchentity>