<dvtablesearchentity dvtablesearchentityid="53d5c70c-96be-f011-bbd2-000d3a5a9505">
  <dvtablesearch>
    <dvtablesearchid>4dbc395e-68c1-4fa8-b1e8-a98d24901173</dvtablesearchid>
  </dvtablesearch>
  <entitylogicalname>bd8bc5b9-775a-470f-ac5e-5eed26444368</entitylogicalname>
  <iscustomizable>1</iscustomizable>
  <name>K192920.pdf</name>
  <statecode>0</statecode>
  <statuscode>1</statuscode>
  <unstructuredfilesearchentityid>
    <unstructuredfilesearchentityid>db4be6a0-3cbd-f011-bbd2-000d3a36bee6</unstructuredfilesearchentityid>
  </unstructuredfilesearchentityid>
</dvtablesearchentity>