<dvtablesearchentity dvtablesearchentityid="67149606-96be-f011-bbd2-000d3a5a9505">
  <dvtablesearch>
    <dvtablesearchid>4dbc395e-68c1-4fa8-b1e8-a98d24901173</dvtablesearchid>
  </dvtablesearch>
  <entitylogicalname>095aebc4-8857-4030-9c61-58c8577e6ec3</entitylogicalname>
  <iscustomizable>1</iscustomizable>
  <name>K250117.pdf</name>
  <statecode>0</statecode>
  <statuscode>1</statuscode>
  <unstructuredfilesearchentityid>
    <unstructuredfilesearchentityid>60b73970-3cbd-f011-bbd2-000d3a36bee6</unstructuredfilesearchentityid>
  </unstructuredfilesearchentityid>
</dvtablesearchentity>