{
    "Trade/Device Name(s)": [
        "CELL-DYN SapphireTM System"
    ],
    "Submitter Information": "Abbott Laboratories",
    "510(k) Number": "K051215",
    "Predicate Device Reference 510(k) Number(s)": [],
    "Regulatory Class": "Class II",
    "Product Code(s)": [
        "GKZ"
    ],
    "Summary Letter Date": "July 21, 2005",
    "Summary Letter Received Date": "May 12, 2004",
    "Submission Date": "May 10, 2004",
    "Regulation Number(s)": [
        "21 CFR 864.5220"
    ],
    "Regulation Name(s)": [
        "Automated differential cell counter"
    ],
    "Analyte Class(es)": [
        "hematology",
        "immunology"
    ],
    "Analyte(s)": [
        "Complete blood count",
        "WBC Differential",
        "NRBC",
        "Reticulocyte",
        "Immature Reticulocyte Fraction",
        "CD61",
        "CD3/4/8"
    ],
    "Specimen Type(s)": [
        "Whole blood"
    ],
    "Specimen Container(s)": [
        "EDTA tube"
    ],
    "Instrument(s)/Platform(s)": [
        "CELL-DYN SapphireTM System"
    ],
    "Method(s)/Technology(ies)": [
        "Impedance",
        "Laser optical scatter",
        "Fluorescence",
        "Optical absorbance"
    ],
    "Methodologies": [
        "Impedance measurement",
        "Optical scatter analysis",
        "Immunofluorescent analysis"
    ],
    "Submission Type(s)": [
        "Analyzer",
        "Instrument",
        "System",
        "Software",
        "Reagent"
    ],
    "Document Summary": "FDA 510(k) summary for the CELL-DYN Sapphire automated hematology analyzer for multiparameter blood analysis and immunophenotyping.",
    "Indications for Use Summary": "Multiparameter automated hematology analyzer for complete blood count with WBC Differential, NRBC, Reticulocyte and Immature Reticulocyte Fraction enumeration, and CD61 and CD3/4/8 immunofluorescent analysis on EDTA-anticoagulated whole blood.",
    "fda_folder": "Hematology"
}