{
    "Trade/Device Name(s)": [
        "VALIDATE\u00ae D-Dimer Calibration Verification/Linearity Test Kit"
    ],
    "Submitter Information": "Maine Standards Company LLC",
    "510(k) Number": "K152961",
    "Predicate Device Reference 510(k) Number(s)": [
        "K100716"
    ],
    "Regulatory Class": "Class II",
    "Product Code(s)": [
        "GGN"
    ],
    "Summary Letter Date": "May 4, 2016",
    "Summary Letter Received Date": "May 5, 2016",
    "Submission Date": "May 31, 2016",
    "Regulation Number(s)": [
        "21 CFR 864.5425"
    ],
    "Regulation Name(s)": [
        "Multipurpose system for in vitro coagulation studies"
    ],
    "Analyte Class(es)": [
        "coagulation"
    ],
    "Analyte(s)": [
        "D-Dimer"
    ],
    "Specimen Type(s)": [
        "Plasma"
    ],
    "Specimen Container(s)": [],
    "Instrument(s)/Platform(s)": [
        "Instrumentation Laboratory TOP instrument system"
    ],
    "Method(s)/Technology(ies)": [
        "Calibration verification",
        "Linearity testing"
    ],
    "Methodologies": [
        "Quantitative determination of linearity",
        "Calibration verification",
        "Verification of reportable range"
    ],
    "Submission Type(s)": [
        "Kit",
        "Calibration Verification",
        "Linearity Test"
    ],
    "Document Summary": "FDA 510(k) summary for VALIDATE\u00ae D-Dimer Calibration Verification/Linearity Test Kit for in vitro determination of D-Dimer linearity and calibration verification in plasma",
    "Indications for Use Summary": "Assayed quality control material for in vitro diagnostic use in the quantitative determination of linearity, calibration verification and verification of reportable range for D-Dimer in plasma by laboratory personnel on automated analyzers",
    "fda_folder": "Hematology"
}