{
    "Trade/Device Name(s)": [
        "A1C EZ Glycohemoglobin Analysis System"
    ],
    "Submitter Information": "BioHermes Co., Ltd",
    "510(k) Number": "K161533",
    "Predicate Device Reference 510(k) Number(s)": [
        "K090413"
    ],
    "Regulatory Class": "Class II; Class I",
    "Product Code(s)": [
        "LCP",
        "JJE"
    ],
    "Summary Letter Date": "May 3, 2017",
    "Summary Letter Received Date": "May 8, 2017",
    "Submission Date": "March 28, 2016",
    "Regulation Number(s)": [
        "21 CFR 864.7470",
        "21 CFR 862.2160"
    ],
    "Regulation Name(s)": [
        "Glycosylated hemoglobin assay",
        "Analyzer, Chemistry (Photometric, Discrete), For Clinical Use"
    ],
    "Analyte Class(es)": [
        "chemistry"
    ],
    "Analyte(s)": [
        "Glycohemoglobin A1c",
        "Hemoglobin A1c"
    ],
    "Specimen Type(s)": [
        "Venous whole blood"
    ],
    "Specimen Container(s)": [
        "K2-EDTA tube",
        "Heparin Sodium tube",
        "Sodium Fluoride tube",
        "Lithium Heparin tube"
    ],
    "Instrument(s)/Platform(s)": [
        "A1C EZ Glycohemoglobin Analysis System analyzer"
    ],
    "Method(s)/Technology(ies)": [
        "Boronate affinity chromatography",
        "Photometric reflectance"
    ],
    "Methodologies": [
        "Quantitative assay",
        "Lateral flow chromatography"
    ],
    "Submission Type(s)": [
        "Assay",
        "Analyzer",
        "Test strip"
    ],
    "Document Summary": "FDA 510(k) summary for BioHermes A1C EZ Glycohemoglobin Analysis System for quantitative measurement of percent HbA1c in venous whole blood using boronate affinity chromatography in clinical laboratories",
    "Indications for Use Summary": "In vitro diagnostic test to quantitatively measure percent glycohemoglobin A1c or fraction mmol/mol in venous whole blood samples for monitoring long term glycemic control in patients previously diagnosed with diabetes; not for screening, diagnosis, or neonatal use; intended for professional use in clinical laboratories",
    "fda_folder": "Hematology"
}