{
    "Trade/Device Name(s)": [
        "HemoTrol WB - Low",
        "HemoTrol WB - Normal",
        "HemoTrol WB - High"
    ],
    "Submitter Information": "Eurotrol B.V.",
    "510(k) Number": "K182744",
    "Predicate Device Reference 510(k) Number(s)": [
        "K964052"
    ],
    "Regulatory Class": "Class II",
    "Product Code(s)": [
        "GGM"
    ],
    "Summary Letter Date": "February 1, 2019",
    "Summary Letter Received Date": "September 28, 2018",
    "Submission Date": "September 26, 2018",
    "Regulation Number(s)": [
        "21 CFR 864.8625"
    ],
    "Regulation Name(s)": [
        "Hematology quality control mixture"
    ],
    "Analyte Class(es)": [
        "hematology"
    ],
    "Analyte(s)": [
        "Hemoglobin"
    ],
    "Specimen Type(s)": [],
    "Specimen Container(s)": [
        "Reclosable plastic primary container"
    ],
    "Instrument(s)/Platform(s)": [
        "HemoCue Hb 301",
        "HemoCue Hb 801"
    ],
    "Method(s)/Technology(ies)": [
        "Spectrophotometric technology"
    ],
    "Methodologies": [],
    "Submission Type(s)": [
        "Quality control material"
    ],
    "Document Summary": "FDA 510(k) summary for Eurotrol HemoTrol WB assayed hemoglobin quality control materials for verification of HemoCue Hb 301 and Hb 801 systems.",
    "Indications for Use Summary": "Assayed quality control material for professional use to verify performance characteristics of HemoCue Hb 301 and Hb 801 hemoglobin analyzers.",
    "fda_folder": "Hematology"
}