<dvtablesearchentity dvtablesearchentityid="c2c133bb-96be-f011-bbd2-000d3a5a9505">
  <dvtablesearch>
    <dvtablesearchid>c87d86dd-0f2f-4eb9-a477-430efbab5760</dvtablesearchid>
  </dvtablesearch>
  <entitylogicalname>c0d2cf5d-3bc6-4c90-abd5-a47aa322e5ba</entitylogicalname>
  <iscustomizable>1</iscustomizable>
  <name>K130189.pdf</name>
  <statecode>0</statecode>
  <statuscode>1</statuscode>
  <unstructuredfilesearchentityid>
    <unstructuredfilesearchentityid>6941026f-37bb-f011-bbd2-7ced8d709b8c</unstructuredfilesearchentityid>
  </unstructuredfilesearchentityid>
</dvtablesearchentity>