<dvtablesearchentity dvtablesearchentityid="f6e4f418-96be-f011-bbd2-000d3a5a9505">
  <dvtablesearch>
    <dvtablesearchid>4dbc395e-68c1-4fa8-b1e8-a98d24901173</dvtablesearchid>
  </dvtablesearch>
  <entitylogicalname>769c5527-5b51-4ee0-a9b6-6c67268a4de8</entitylogicalname>
  <iscustomizable>1</iscustomizable>
  <name>K170463.pdf</name>
  <statecode>0</statecode>
  <statuscode>1</statuscode>
  <unstructuredfilesearchentityid>
    <unstructuredfilesearchentityid>2eb64ae3-3cbd-f011-bbd2-000d3a36bee6</unstructuredfilesearchentityid>
  </unstructuredfilesearchentityid>
</dvtablesearchentity>