<dvtablesearchentity dvtablesearchentityid="f9f0387b-81be-f011-bbd2-000d3a5a9505">
  <dvtablesearch>
    <dvtablesearchid>3f3cb599-87c9-4eca-aff1-d1c5a6e55c1a</dvtablesearchid>
  </dvtablesearch>
  <entitylogicalname>9334ac67-7031-4336-bbcf-f584253e5765</entitylogicalname>
  <iscustomizable>1</iscustomizable>
  <name>K100937.pdf</name>
  <statecode>0</statecode>
  <statuscode>1</statuscode>
  <unstructuredfilesearchentityid>
    <unstructuredfilesearchentityid>c3922c38-3ebd-f011-bbd2-000d3a36bee6</unstructuredfilesearchentityid>
  </unstructuredfilesearchentityid>
</dvtablesearchentity>