<dvtablesearchentity dvtablesearchentityid="91e27326-81be-f011-bbd2-000d3a5a9505">
  <dvtablesearch>
    <dvtablesearchid>3f3cb599-87c9-4eca-aff1-d1c5a6e55c1a</dvtablesearchid>
  </dvtablesearch>
  <entitylogicalname>1854037c-5543-4f78-9297-b5ffc4bb167a</entitylogicalname>
  <iscustomizable>1</iscustomizable>
  <name>K101037.pdf</name>
  <statecode>0</statecode>
  <statuscode>1</statuscode>
  <unstructuredfilesearchentityid>
    <unstructuredfilesearchentityid>8a5026cc-3dbd-f011-bbd2-000d3a36bee6</unstructuredfilesearchentityid>
  </unstructuredfilesearchentityid>
</dvtablesearchentity>