<dvtablesearchentity dvtablesearchentityid="ca82f2bd-95be-f011-bbd2-000d3a5a9505">
  <dvtablesearch>
    <dvtablesearchid>4dbc395e-68c1-4fa8-b1e8-a98d24901173</dvtablesearchid>
  </dvtablesearch>
  <entitylogicalname>23b0d097-2337-44e0-82e1-033e68b07e69</entitylogicalname>
  <iscustomizable>1</iscustomizable>
  <name>K213808.pdf</name>
  <statecode>0</statecode>
  <statuscode>1</statuscode>
  <unstructuredfilesearchentityid>
    <unstructuredfilesearchentityid>1459527d-3abd-f011-bbd2-000d3a36bee6</unstructuredfilesearchentityid>
  </unstructuredfilesearchentityid>
</dvtablesearchentity>