<dvtablesearchentity dvtablesearchentityid="6f2c153f-80be-f011-bbd2-000d3a5a9505">
  <dvtablesearch>
    <dvtablesearchid>3f3cb599-87c9-4eca-aff1-d1c5a6e55c1a</dvtablesearchid>
  </dvtablesearch>
  <entitylogicalname>3b5c1425-b216-4ab7-9411-025c91135b17</entitylogicalname>
  <iscustomizable>1</iscustomizable>
  <name>K113098.pdf</name>
  <statecode>0</statecode>
  <statuscode>1</statuscode>
  <unstructuredfilesearchentityid>
    <unstructuredfilesearchentityid>f1524d83-3abd-f011-bbd2-000d3a36bee6</unstructuredfilesearchentityid>
  </unstructuredfilesearchentityid>
</dvtablesearchentity>