<dvtablesearchentity dvtablesearchentityid="0f5b9c41-77be-f011-bbd2-000d3a5a9505">
  <dvtablesearch>
    <dvtablesearchid>5be7d29c-5488-4092-935a-dd147ca98298</dvtablesearchid>
  </dvtablesearch>
  <entitylogicalname>b4f7e7eb-358f-4eb6-92a2-c83cbc257f60</entitylogicalname>
  <iscustomizable>1</iscustomizable>
  <name>K080167.pdf</name>
  <statecode>0</statecode>
  <statuscode>1</statuscode>
  <unstructuredfilesearchentityid>
    <unstructuredfilesearchentityid>138429e4-3dbd-f011-bbd2-000d3a36bee6</unstructuredfilesearchentityid>
  </unstructuredfilesearchentityid>
</dvtablesearchentity>